{
  "generated_at": "2026-05-04T12:12:00.949430Z",
  "mode": "sandbox",
  "portfolio_value": 60000.0,
  "total_invested": 118862.0,
  "current_value": 119656.0,
  "net_pnl": 795.0,
  "net_pnl_pct": 0.67,
  "breadth": 9,
  "breadth_max": 11,
  "target_alloc": {
    "MON100.NS": 33.3,
    "CPSEETF.NS": 33.3,
    "JUNIORBEES.NS": 33.3,
    "LIQUIDBEES.NS": 0.0
  },
  "positions": [
    {
      "ticker": "MON100.NS",
      "shares": 133.0,
      "avg_cost": 297.12,
      "live_price": 301.87,
      "invested": 39517.0,
      "current": 40149.0,
      "pnl": 632.0,
      "pnl_pct": 1.6
    },
    {
      "ticker": "CPSEETF.NS",
      "shares": 370.0,
      "avg_cost": 107.9,
      "live_price": 108.08,
      "invested": 39924.0,
      "current": 39990.0,
      "pnl": 66.0,
      "pnl_pct": 0.16
    },
    {
      "ticker": "JUNIORBEES.NS",
      "shares": 52.0,
      "avg_cost": 758.09,
      "live_price": 759.96,
      "invested": 39421.0,
      "current": 39518.0,
      "pnl": 97.0,
      "pnl_pct": 0.25
    }
  ],
  "usd_inr": 94.98,
  "last_run_date": "2026-05-01",
  "signal_date": "2026-04-23",
  "market_status": "CLOSED \u2014 last close shown",
  "last_pnl_update": "2026-05-04 12:12 UTC"
}